open_xtract/__init__.py
open_xtract/_extract.py
open_xtract/exceptions.py
open_xtract-0.1.4.dist-info/METADATA
open_xtract-0.1.4.dist-info/WHEEL
open_xtract-0.1.4.dist-info/RECORD
