Metadata-Version: 2.4
Name: open-xtract
Version: 0.1.4
Summary: Extract structured data from documents, images, audio, and video using LLMs
Project-URL: Homepage, https://github.com/colesmcintosh/open-xtract-v2
Project-URL: Repository, https://github.com/colesmcintosh/open-xtract-v2
Project-URL: Issues, https://github.com/colesmcintosh/open-xtract-v2/issues
Author: Cole McIntosh
License-Expression: MIT
Keywords: ai,document,extraction,llm,pydantic,structured-data
Classifier: Development Status :: 3 - Alpha
Classifier: Intended Audience :: Developers
Classifier: License :: OSI Approved :: MIT License
Classifier: Programming Language :: Python :: 3
Classifier: Programming Language :: Python :: 3.12
Classifier: Programming Language :: Python :: 3.13
Classifier: Topic :: Scientific/Engineering :: Artificial Intelligence
Requires-Python: >=3.12
Requires-Dist: pydantic-ai-slim[google,logfire]>=1.37.0
Requires-Dist: pydantic>=2.12.5
